litcorpt/__init__.py
litcorpt/constants.py
litcorpt/epub.py
litcorpt/main.py
litcorpt/model.py
litcorpt/py.typed
litcorpt/search.py
litcorpt/utils.py
litcorpt-0.0.8.dist-info/LICENSE
litcorpt-0.0.8.dist-info/METADATA
litcorpt-0.0.8.dist-info/WHEEL
litcorpt-0.0.8.dist-info/top_level.txt
litcorpt-0.0.8.dist-info/RECORD
