Metadata-Version: 2.1
Name: litcorpt
Version: 0.0.8
Summary: API to access Portuguese Literary Corpus
Home-page: https://github.com/igormorgado/litcorpt
Author: Igor Morgado
Author-email: morgado.igor@gmail.com
License: UNKNOWN
Project-URL: Bug Tracker, https://github.com/igormorgado/litcorpt/issues
Platform: UNKNOWN
Classifier: Programming Language :: Python :: 3
Classifier: License :: OSI Approved :: MIT License
Classifier: Operating System :: OS Independent
Requires-Python: >=3.6
License-File: LICENSE
Requires-Dist: tinydb
Requires-Dist: requests
Requires-Dist: pydantic
Requires-Dist: python-dotenv
Requires-Dist: bs4
Requires-Dist: unidecode
Requires-Dist: ebooklib
